MANIFEST.in
setup.py
docs/CHANGELOG.rst
docs/README.rst
unishark/__init__.py
unishark/decorator.py
unishark/exception.py
unishark/loader.py
unishark/main.py
unishark/reporter.py
unishark/result.py
unishark/runner.py
unishark/suite.py
unishark/util.py
unishark.egg-info/PKG-INFO
unishark.egg-info/SOURCES.txt
unishark.egg-info/dependency_links.txt
unishark.egg-info/pbr.json
unishark.egg-info/requires.txt
unishark.egg-info/top_level.txt
unishark/templates/index.html
unishark/templates/junit_suite_result.xml
unishark/templates/junit_suites_result.xml
unishark/templates/overview.html
unishark/templates/report.html