Metadata-Version: 1.1
Name: unishark
Version: 0.3.2
Summary: A test framework extending unittest, providing flexible test suites config, concurrent execution, Html/XUnit reports, and data driven utility.
Home-page: https://github.com/twitter/unishark
Author: Ying Ni
Author-email: niying7@gmail.com
License: Apache License, Version 2.0
Keywords: test framework,unittest extension,concurrent,data driven
Platform: UNKNOWN
Classifier: Development Status :: 5 - Production/Stable
Classifier: Intended Audience :: Developers
Classifier: Topic :: Software Development :: Testing
Classifier: License :: OSI Approved :: Apache Software License
Classifier: Operating System :: POSIX :: Linux
Classifier: Operating System :: MacOS :: MacOS X
Classifier: Programming Language :: Python :: 2.7
Classifier: Programming Language :: Python :: 3.3
Classifier: Programming Language :: Python :: 3.4
Classifier: Programming Language :: Python :: 3.5
Classifier: Programming Language :: Python :: Implementation :: Jython
